<!--
	Copyright 2024 MicroEJ Corp. All rights reserved.
	Use of this source code is governed by a BSD-style license that can be found with this software.
-->
<animated-vector xmlns:android="http://schemas.android.com/apk/res/android" xmlns:aapt="http://schemas.android.com/aapt"><aapt:attr name="android:drawable"><vector android:height="90dp" android:width="310dp" android:viewportHeight="90" android:viewportWidth="310"><group android:name="_R_G"><group android:name="_R_G_L_1_G" android:translateX="4.652999999999992" android:translateY="-40.928"><group android:name="_R_G_L_1_G_D_0_P_0_G_0_T_0" android:translateX="150.347" android:translateY="76.365" android:scaleX="0.8" android:scaleY="0.8"><path android:name="_R_G_L_1_G_D_0_P_0" android:fillColor="#ffffff" android:fillAlpha="0.05" android:fillType="nonZero" android:pathData=" M112.5 37.5 C112.5,37.5 -112.5,37.5 -112.5,37.5 C-133.21,37.5 -150,20.71 -150,0 C-150,-20.71 -133.21,-37.5 -112.5,-37.5 C-112.5,-37.5 112.5,-37.5 112.5,-37.5 C133.21,-37.5 150,-20.71 150,0 C150,20.71 133.21,37.5 112.5,37.5c "/></group></group><group android:name="_R_G_L_0_G_N_1_T_0" android:translateX="155" android:translateY="45"><group android:name="_R_G_L_0_G_T_1" android:translateX="-90.5" android:translateY="7.5" android:scaleX="1.67492" android:scaleY="1.67492"><group android:name="_R_G_L_0_G" android:translateX="-14" android:translateY="-14"><path android:name="_R_G_L_0_G_D_0_P_0" android:fillColor="#16406e" android:fillAlpha="0" android:fillType="nonZero" android:pathData=" M21.34 9.66 C20.95,9.27 20.32,9.27 19.93,9.66 C19.37,10.22 17.19,11.65 13.79,11.65 C10.39,11.65 8.21,10.22 7.66,9.66 C7.27,9.27 6.63,9.27 6.24,9.66 C5.85,10.06 5.85,10.69 6.24,11.08 C6.89,11.73 8.35,12.67 10.43,13.22 C10.43,13.22 9.38,21.64 9.38,21.64 C9.36,21.84 9.39,22.03 9.48,22.21 C9.65,22.56 10.01,22.77 10.38,22.77 C10.53,22.77 10.68,22.73 10.82,22.66 C11.05,22.55 11.22,22.35 11.31,22.12 C12.18,19.81 13.36,18.27 13.79,18.21 C14.22,18.27 15.41,19.81 16.27,22.12 C16.45,22.59 16.96,22.85 17.45,22.73 C17.94,22.61 18.27,22.14 18.2,21.64 C18.2,21.64 17.15,13.22 17.15,13.22 C19.24,12.67 20.69,11.73 21.34,11.08 C21.73,10.69 21.73,10.06 21.34,9.66c "/><path android:name="_R_G_L_0_G_D_1_P_0" android:fillColor="#16406e" android:fillAlpha="0" android:fillType="nonZero" android:pathData=" M13.79 5.95 C12.61,5.95 11.65,6.91 11.65,8.09 C11.65,9.27 12.61,10.23 13.79,10.23 C14.97,10.23 15.93,9.27 15.93,8.09 C15.93,6.91 14.97,5.95 13.79,5.95c "/><path android:name="_R_G_L_0_G_D_2_P_0" android:fillColor="#16406e" android:fillAlpha="0" android:fillType="nonZero" android:pathData=" M13.79 27.34 C6.33,27.34 0.25,21.26 0.25,13.79 C0.25,6.32 6.33,0.25 13.79,0.25 C21.26,0.25 27.33,6.32 27.33,13.79 C27.33,21.26 21.26,27.34 13.79,27.34c  M13.79 2.25 C7.43,2.25 2.25,7.43 2.25,13.79 C2.25,20.16 7.43,25.34 13.79,25.34 C20.16,25.34 25.33,20.16 25.33,13.79 C25.33,7.43 20.16,2.25 13.79,2.25c "/></group></group></group></group><group android:name="time_group"/></vector></aapt:attr><target android:name="_R_G_L_1_G_D_0_P_0"><aapt:attr name="android:animation"><set android:ordering="together"><objectAnimator android:propertyName="fillAlpha" android:duration="400" android:startOffset="0" android:valueFrom="0.05" android:valueTo="1" android:valueType="floatType"><aapt:attr name="android:interpolator"><pathInterpolator android:pathData="M 0.0,0.0 c0.167,0.167 0.271,1 1.0,1.0"/></aapt:attr></objectAnimator><objectAnimator android:propertyName="fillAlpha" android:duration="200" android:startOffset="400" android:valueFrom="1" android:valueTo="0" android:valueType="floatType"><aapt:attr name="android:interpolator"><pathInterpolator android:pathData="M 0.0,0.0 c0.167,0.167 0.833,0.833 1.0,1.0"/></aapt:attr></objectAnimator></set></aapt:attr></target><target android:name="_R_G_L_1_G_D_0_P_0_G_0_T_0"><aapt:attr name="android:animation"><set android:ordering="together"><objectAnimator android:propertyName="translateXY" android:duration="260" android:startOffset="0" android:propertyXName="translateX" android:propertyYName="translateY" android:pathData="M 150.347,76.365C 150.347,79.198 150.347,90.532 150.347,93.365"><aapt:attr name="android:interpolator"><pathInterpolator android:pathData="M 0.0,0.0 c0.167,0.167 0.667,1 1.0,1.0"/></aapt:attr></objectAnimator></set></aapt:attr></target><target android:name="_R_G_L_1_G_D_0_P_0_G_0_T_0"><aapt:attr name="android:animation"><set android:ordering="together"><objectAnimator android:propertyName="scaleX" android:duration="260" android:startOffset="0" android:valueFrom="0.8" android:valueTo="1" android:valueType="floatType"><aapt:attr name="android:interpolator"><pathInterpolator android:pathData="M 0.0,0.0 c0.167,0.167 0.667,1 1.0,1.0"/></aapt:attr></objectAnimator><objectAnimator android:propertyName="scaleY" android:duration="260" android:startOffset="0" android:valueFrom="0.8" android:valueTo="1" android:valueType="floatType"><aapt:attr name="android:interpolator"><pathInterpolator android:pathData="M 0.0,0.0 c0.167,0.167 0.667,1 1.0,1.0"/></aapt:attr></objectAnimator></set></aapt:attr></target><target android:name="_R_G_L_1_G_D_0_P_0"><aapt:attr name="android:animation"><set android:ordering="together"><objectAnimator android:propertyName="pathData" android:duration="400" android:startOffset="0" android:valueFrom="M112.5 37.5 C112.5,37.5 -112.5,37.5 -112.5,37.5 C-133.21,37.5 -150,20.71 -150,0 C-150,-20.71 -133.21,-37.5 -112.5,-37.5 C-112.5,-37.5 112.5,-37.5 112.5,-37.5 C133.21,-37.5 150,-20.71 150,0 C150,20.71 133.21,37.5 112.5,37.5c " android:valueTo="M112.5 37.5 C112.5,37.5 -112.5,37.5 -112.5,37.5 C-133.21,37.5 -150,20.71 -150,0 C-150,-20.71 -133.21,-37.5 -112.5,-37.5 C-112.5,-37.5 112.5,-37.5 112.5,-37.5 C133.21,-37.5 150,-20.71 150,0 C150,20.71 133.21,37.5 112.5,37.5c " android:valueType="pathType"><aapt:attr name="android:interpolator"><pathInterpolator android:pathData="M 0.0,0.0 c0.167,0.167 0.833,0.833 1.0,1.0"/></aapt:attr></objectAnimator><objectAnimator android:propertyName="pathData" android:duration="200" android:startOffset="400" android:valueFrom="M112.5 37.5 C112.5,37.5 -112.5,37.5 -112.5,37.5 C-133.21,37.5 -150,20.71 -150,0 C-150,-20.71 -133.21,-37.5 -112.5,-37.5 C-112.5,-37.5 112.5,-37.5 112.5,-37.5 C133.21,-37.5 150,-20.71 150,0 C150,20.71 133.21,37.5 112.5,37.5c " android:valueTo="M-109.72 37.5 C-109.72,37.5 -112.5,37.5 -112.5,37.5 C-133.21,37.5 -150,20.71 -150,0 C-150,-20.71 -133.21,-37.5 -112.5,-37.5 C-112.5,-37.5 -109.72,-37.5 -109.72,-37.5 C-89.01,-37.5 -72.22,-20.71 -72.22,0 C-72.22,20.71 -89.01,37.5 -109.72,37.5c " android:valueType="pathType"><aapt:attr name="android:interpolator"><pathInterpolator android:pathData="M 0.0,0.0 c0.167,0.167 0.833,0.833 1.0,1.0"/></aapt:attr></objectAnimator></set></aapt:attr></target><target android:name="_R_G_L_0_G_D_0_P_0"><aapt:attr name="android:animation"><set android:ordering="together"><objectAnimator android:propertyName="fillAlpha" android:duration="220" android:startOffset="0" android:valueFrom="0" android:valueTo="0" android:valueType="floatType"><aapt:attr name="android:interpolator"><pathInterpolator android:pathData="M 0.0,0.0 c0.167,0.167 0.833,0.833 1.0,1.0"/></aapt:attr></objectAnimator><objectAnimator android:propertyName="fillAlpha" android:duration="100" android:startOffset="220" android:valueFrom="0" android:valueTo="1" android:valueType="floatType"><aapt:attr name="android:interpolator"><pathInterpolator android:pathData="M 0.0,0.0 c0.167,0.167 0.833,0.833 1.0,1.0"/></aapt:attr></objectAnimator><objectAnimator android:propertyName="fillAlpha" android:duration="80" android:startOffset="320" android:valueFrom="1" android:valueTo="1" android:valueType="floatType"><aapt:attr name="android:interpolator"><pathInterpolator android:pathData="M 0.0,0.0 c0.167,0.167 0.833,0.833 1.0,1.0"/></aapt:attr></objectAnimator><objectAnimator android:propertyName="fillAlpha" android:duration="200" android:startOffset="400" android:valueFrom="1" android:valueTo="0" android:valueType="floatType"><aapt:attr name="android:interpolator"><pathInterpolator android:pathData="M 0.0,0.0 c0.167,0.167 0.833,0.833 1.0,1.0"/></aapt:attr></objectAnimator></set></aapt:attr></target><target android:name="_R_G_L_0_G_D_1_P_0"><aapt:attr name="android:animation"><set android:ordering="together"><objectAnimator android:propertyName="fillAlpha" android:duration="220" android:startOffset="0" android:valueFrom="0" android:valueTo="0" android:valueType="floatType"><aapt:attr name="android:interpolator"><pathInterpolator android:pathData="M 0.0,0.0 c0.167,0.167 0.833,0.833 1.0,1.0"/></aapt:attr></objectAnimator><objectAnimator android:propertyName="fillAlpha" android:duration="100" android:startOffset="220" android:valueFrom="0" android:valueTo="1" android:valueType="floatType"><aapt:attr name="android:interpolator"><pathInterpolator android:pathData="M 0.0,0.0 c0.167,0.167 0.833,0.833 1.0,1.0"/></aapt:attr></objectAnimator><objectAnimator android:propertyName="fillAlpha" android:duration="80" android:startOffset="320" android:valueFrom="1" android:valueTo="1" android:valueType="floatType"><aapt:attr name="android:interpolator"><pathInterpolator android:pathData="M 0.0,0.0 c0.167,0.167 0.833,0.833 1.0,1.0"/></aapt:attr></objectAnimator><objectAnimator android:propertyName="fillAlpha" android:duration="200" android:startOffset="400" android:valueFrom="1" android:valueTo="0" android:valueType="floatType"><aapt:attr name="android:interpolator"><pathInterpolator android:pathData="M 0.0,0.0 c0.167,0.167 0.833,0.833 1.0,1.0"/></aapt:attr></objectAnimator></set></aapt:attr></target><target android:name="_R_G_L_0_G_D_2_P_0"><aapt:attr name="android:animation"><set android:ordering="together"><objectAnimator android:propertyName="fillAlpha" android:duration="220" android:startOffset="0" android:valueFrom="0" android:valueTo="0" android:valueType="floatType"><aapt:attr name="android:interpolator"><pathInterpolator android:pathData="M 0.0,0.0 c0.167,0.167 0.833,0.833 1.0,1.0"/></aapt:attr></objectAnimator><objectAnimator android:propertyName="fillAlpha" android:duration="100" android:startOffset="220" android:valueFrom="0" android:valueTo="1" android:valueType="floatType"><aapt:attr name="android:interpolator"><pathInterpolator android:pathData="M 0.0,0.0 c0.167,0.167 0.833,0.833 1.0,1.0"/></aapt:attr></objectAnimator><objectAnimator android:propertyName="fillAlpha" android:duration="80" android:startOffset="320" android:valueFrom="1" android:valueTo="1" android:valueType="floatType"><aapt:attr name="android:interpolator"><pathInterpolator android:pathData="M 0.0,0.0 c0.167,0.167 0.833,0.833 1.0,1.0"/></aapt:attr></objectAnimator><objectAnimator android:propertyName="fillAlpha" android:duration="200" android:startOffset="400" android:valueFrom="1" android:valueTo="0" android:valueType="floatType"><aapt:attr name="android:interpolator"><pathInterpolator android:pathData="M 0.0,0.0 c0.167,0.167 0.833,0.833 1.0,1.0"/></aapt:attr></objectAnimator></set></aapt:attr></target><target android:name="_R_G_L_0_G_T_1"><aapt:attr name="android:animation"><set android:ordering="together"><objectAnimator android:propertyName="translateXY" android:duration="220" android:startOffset="0" android:propertyXName="translateX" android:propertyYName="translateY" android:pathData="M -90.5,7.5C -93.833,7.5 -87.167,7.5 -90.5,7.5"><aapt:attr name="android:interpolator"><pathInterpolator android:pathData="M 0.0,0.0 c0.167,0.167 0.833,0.833 1.0,1.0"/></aapt:attr></objectAnimator><objectAnimator android:propertyName="translateXY" android:duration="100" android:startOffset="220" android:propertyXName="translateX" android:propertyYName="translateY" android:pathData="M -90.5,7.5C -93.833,7.5 -107.167,7.5 -110.5,7.5"><aapt:attr name="android:interpolator"><pathInterpolator android:pathData="M 0.0,0.0 c0.167,0.167 0.833,0.833 1.0,1.0"/></aapt:attr></objectAnimator></set></aapt:attr></target><target android:name="_R_G_L_0_G_N_1_T_0"><aapt:attr name="android:animation"><set android:ordering="together"><objectAnimator android:propertyName="translateXY" android:duration="240" android:startOffset="0" android:propertyXName="translateX" android:propertyYName="translateY" android:pathData="M 155,45C 155,45 155,45 155,45"><aapt:attr name="android:interpolator"><pathInterpolator android:pathData="M 0.0,0.0 c0.167,0.167 0.833,0.833 1.0,1.0"/></aapt:attr></objectAnimator><objectAnimator android:propertyName="translateXY" android:duration="80" android:startOffset="240" android:propertyXName="translateX" android:propertyYName="translateY" android:pathData="M 155,45C 155,45 155,45 155,45"><aapt:attr name="android:interpolator"><pathInterpolator android:pathData="M 0.0,0.0 c0.167,0.167 0.833,0.833 1.0,1.0"/></aapt:attr></objectAnimator></set></aapt:attr></target><target android:name="time_group"><aapt:attr name="android:animation"><set android:ordering="together"><objectAnimator android:propertyName="translateX" android:duration="600" android:startOffset="0" android:valueFrom="0" android:valueTo="1" android:valueType="floatType"/></set></aapt:attr></target></animated-vector>